{
  "id": "TR_TS_019_2011",
  "number": "019/2011",
  "shortName": "ТР ТС 019/2011",
  "fullName": "О безопасности средств индивидуальной защиты",
  "decisionNumber": "N 878",
  "decisionDate": "2011-12-09",
  "validFrom": "2012-06-01",
  "lastUpdated": "2025-12-18",
  "garantId": 12191612,
  "garantUrl": "https://base.garant.ru/12191612/",

  "scope": {
    "description": "Технический регламент распространяется на средства индивидуальной защиты, новые и выпускаемые в обращение на территории Таможенного союза",
    "includes": [
      "СИЗ органов дыхания фильтрующие",
      "СИЗ органов дыхания изолирующие",
      "Одежда специальная защитная",
      "СИЗ рук (перчатки, рукавицы)",
      "СИЗ ног (обувь защитная)",
      "СИЗ головы (каски, каскетки)",
      "СИЗ лица и глаз (очки, щитки)",
      "СИЗ органа слуха (наушники, вкладыши)",
      "СИЗ от падения с высоты (привязи, стропы)",
      "Средства дерматологические защитные"
    ],
    "excludes": [
      "СИЗ для спортивных состязаний",
      "СИЗ для пожарной охраны (специально разработанные)",
      "СИЗ для авиации, космоса и подводных работ",
      "СИЗ для медицинских целей и микробиологии",
      "СИЗ в качестве образцов для выставок",
      "СИЗ для защиты от биологического/химического оружия"
    ]
  },

  "confirmationType": "mixed",
  "confirmationNote": "Сертификация для СИЗ от высоких рисков (1 класс), декларирование для СИЗ от низких рисков (2 класс)",

  "productGroups": [
    {
      "id": "siz_1",
      "name": "СИЗ органов дыхания (СИЗОД)",
      "description": "Средства защиты органов дыхания от вредных веществ",
      "confirmationType": "certificate",
      "schemes": ["1с", "3с", "4с"],
      "schemeNote": "Обязательная СЕРТИФИКАЦИЯ - СИЗ 1 класса риска",
      "products": [
        "Противогазы фильтрующие",
        "Противогазы изолирующие",
        "Респираторы фильтрующие",
        "Самоспасатели фильтрующие",
        "Самоспасатели изолирующие",
        "Дыхательные аппараты со сжатым воздухом",
        "Полумаски фильтрующие (FFP1, FFP2, FFP3)"
      ],
      "tnvedCodes": [
        {"code": "9020 00 000", "name": "Оборудование дыхательное прочее и противогазы"},
        {"code": "6307 90 980 9", "name": "Маски защитные текстильные"}
      ],
      "validity": "до 5 лет",
      "keywords": ["противогаз", "респиратор", "СИЗОД", "самоспасатель", "полумаска FFP"]
    },
    {
      "id": "siz_2",
      "name": "СИЗ от падения с высоты",
      "description": "Средства защиты от падения с высоты",
      "confirmationType": "certificate",
      "schemes": ["1с", "3с", "4с"],
      "schemeNote": "Обязательная СЕРТИФИКАЦИЯ - СИЗ 1 класса риска",
      "products": [
        "Привязи страховочные (пояс предохранительный лямочный)",
        "Привязи удерживающие (пояс безлямочный)",
        "Стропы страховочные",
        "Амортизаторы",
        "Карабины соединительные",
        "Блокирующие устройства",
        "Анкерные устройства",
        "Индивидуальные спасательные устройства (ИСУ)"
      ],
      "tnvedCodes": [
        {"code": "6307 20 000 0", "name": "Пояса и жилеты спасательные"},
        {"code": "8308 90 000 0", "name": "Карабины, застежки"}
      ],
      "keywords": ["привязь страховочная", "пояс монтажный", "карабин", "строп"]
    },
    {
      "id": "siz_3",
      "name": "Одежда специальная защитная",
      "description": "Защитная одежда для различных условий труда",
      "confirmationType": "mixed",
      "products": [
        "Костюмы защитные от механических воздействий - ДЕКЛАРАЦИЯ (2 класс)",
        "Костюмы защитные от химических факторов - СЕРТИФИКАТ (1 класс)",
        "Костюмы защитные от радиоактивных веществ - СЕРТИФИКАТ (1 класс)",
        "Костюмы защитные от теплового излучения - СЕРТИФИКАТ (1 класс)",
        "Жилеты сигнальные повышенной видимости - ДЕКЛАРАЦИЯ (2 класс)",
        "Костюмы от пониженных температур - ДЕКЛАРАЦИЯ (2 класс)",
        "Фартуки защитные - ДЕКЛАРАЦИЯ (2 класс)",
        "Халаты защитные - ДЕКЛАРАЦИЯ (2 класс)"
      ],
      "tnvedCodes": [
        {"code": "6210", "name": "Одежда из тканей с покрытием"},
        {"code": "6211", "name": "Костюмы спортивные, комбинезоны"},
        {"code": "6114", "name": "Одежда трикотажная прочая"}
      ],
      "keywords": ["спецодежда", "костюм защитный", "комбинезон", "жилет сигнальный"]
    },
    {
      "id": "siz_4",
      "name": "СИЗ головы",
      "description": "Средства защиты головы",
      "confirmationType": "mixed",
      "products": [
        "Каски защитные промышленные - СЕРТИФИКАТ (1 класс)",
        "Каскетки защитные - ДЕКЛАРАЦИЯ (2 класс)",
        "Подшлемники утепляющие - ДЕКЛАРАЦИЯ (2 класс)"
      ],
      "tnvedCodes": [
        {"code": "6506 10", "name": "Шлемы защитные"}
      ],
      "keywords": ["каска защитная", "каскетка", "шлем строительный"]
    },
    {
      "id": "siz_5",
      "name": "СИЗ глаз и лица",
      "description": "Средства защиты органов зрения и лица",
      "confirmationType": "mixed",
      "products": [
        "Очки защитные от механических повреждений - ДЕКЛАРАЦИЯ (2 класс)",
        "Очки защитные от излучений (сварочные) - СЕРТИФИКАТ (1 класс)",
        "Очки защитные от химических факторов - СЕРТИФИКАТ (1 класс)",
        "Щитки защитные лицевые - условно по рискам",
        "Маски сварщика - СЕРТИФИКАТ (1 класс)"
      ],
      "tnvedCodes": [
        {"code": "9004 90", "name": "Очки защитные и прочие"}
      ],
      "keywords": ["очки защитные", "щиток лицевой", "маска сварщика"]
    },
    {
      "id": "siz_6",
      "name": "СИЗ рук",
      "description": "Средства защиты рук",
      "confirmationType": "mixed",
      "products": [
        "Перчатки защитные от механических воздействий - ДЕКЛАРАЦИЯ (2 класс)",
        "Перчатки защитные от химических факторов - СЕРТИФИКАТ (1 класс)",
        "Перчатки защитные от вибрации - ДЕКЛАРАЦИЯ (2 класс)",
        "Перчатки защитные от электрического тока - СЕРТИФИКАТ (1 класс)",
        "Перчатки термостойкие - СЕРТИФИКАТ (1 класс)",
        "Рукавицы защитные - условно по рискам",
        "Краги сварщика - СЕРТИФИКАТ (1 класс)"
      ],
      "tnvedCodes": [
        {"code": "6116", "name": "Перчатки трикотажные"},
        {"code": "6216 00 000 0", "name": "Перчатки прочие"},
        {"code": "4015 19 000 0", "name": "Перчатки резиновые"}
      ],
      "keywords": ["перчатки защитные", "рукавицы", "краги"]
    },
    {
      "id": "siz_7",
      "name": "СИЗ ног (обувь защитная)",
      "description": "Защитная обувь",
      "confirmationType": "mixed",
      "products": [
        "Ботинки с защитным подноском - СЕРТИФИКАТ (1 класс)",
        "Сапоги защитные от химических факторов - СЕРТИФИКАТ (1 класс)",
        "Сапоги диэлектрические - СЕРТИФИКАТ (1 класс)",
        "Ботинки утеплённые - ДЕКЛАРАЦИЯ (2 класс)",
        "Тапочки рабочие антистатические - ДЕКЛАРАЦИЯ (2 класс)"
      ],
      "tnvedCodes": [
        {"code": "6401", "name": "Обувь водонепроницаемая"},
        {"code": "6402", "name": "Обувь на подошве и с верхом из резины или пластмассы"},
        {"code": "6403", "name": "Обувь на подошве из резины, пластмассы, кожи"},
        {"code": "6404", "name": "Обувь на подошве из резины или пластмассы с текстильным верхом"}
      ],
      "keywords": ["обувь защитная", "ботинки с подноском", "сапоги резиновые"]
    },
    {
      "id": "siz_8",
      "name": "СИЗ органа слуха",
      "description": "Средства защиты органа слуха от шума",
      "confirmationType": "declaration",
      "schemes": ["1д", "2д", "3д", "4д", "6д"],
      "schemeNote": "ДЕКЛАРИРОВАНИЕ - СИЗ 2 класса риска",
      "products": [
        "Наушники противошумные",
        "Вкладыши противошумные (беруши)",
        "Шлемы противошумные"
      ],
      "tnvedCodes": [
        {"code": "9021 90 900 0", "name": "Приспособления для компенсации дефектов"}
      ],
      "keywords": ["наушники противошумные", "беруши", "вкладыши противошумные"]
    },
    {
      "id": "siz_9",
      "name": "Дерматологические СИЗ",
      "description": "Средства защиты и очистки кожи",
      "confirmationType": "declaration",
      "schemes": ["1д", "2д", "3д", "4д", "6д"],
      "schemeNote": "ДЕКЛАРИРОВАНИЕ",
      "products": [
        "Кремы защитные гидрофобные",
        "Кремы защитные гидрофильные",
        "Очищающие пасты и гели",
        "Восстанавливающие кремы",
        "Защитные мази от вредных веществ"
      ],
      "keywords": ["крем защитный", "паста очищающая", "дерматологическое СИЗ"]
    }
  ],

  "confirmationForms": {
    "certificate": {
      "description": "Для СИЗ 1 класса риска (сложные, от смертельных рисков)",
      "schemes": [
        {
          "id": "1с",
          "name": "Схема 1с",
          "applicableTo": "Серийное производство СИЗ 1 класса",
          "requirements": [
            "Испытания типовых образцов в аккредитованной лаборатории",
            "Анализ состояния производства",
            "Инспекционный контроль"
          ],
          "validity": "до 5 лет"
        },
        {
          "id": "3с",
          "name": "Схема 3с",
          "applicableTo": "Партия СИЗ 1 класса",
          "requirements": [
            "Испытания образцов из партии"
          ],
          "validity": "на партию"
        },
        {
          "id": "4с",
          "name": "Схема 4с",
          "applicableTo": "Единичное изделие СИЗ 1 класса",
          "requirements": [
            "Испытания единичного образца"
          ],
          "validity": "на единичное изделие"
        }
      ]
    },
    "declaration": {
      "description": "Для СИЗ 2 класса риска (простые, от минимальных рисков)",
      "schemes": [
        {
          "id": "1д",
          "name": "Схема 1д",
          "applicableTo": "Серийное производство СИЗ 2 класса",
          "requirements": [
            "Испытания в собственной или аккредитованной лаборатории",
            "Производственный контроль"
          ],
          "validity": "до 3 лет"
        },
        {
          "id": "2д",
          "name": "Схема 2д",
          "applicableTo": "Партия СИЗ 2 класса",
          "requirements": [
            "Испытания образцов из партии"
          ],
          "validity": "на партию"
        },
        {
          "id": "3д",
          "name": "Схема 3д",
          "applicableTo": "Серийное производство (испытания в АИЛ)",
          "requirements": [
            "Испытания в аккредитованной лаборатории",
            "Производственный контроль"
          ],
          "validity": "до 3 лет"
        },
        {
          "id": "4д",
          "name": "Схема 4д",
          "applicableTo": "Партия (испытания в АИЛ)",
          "requirements": [
            "Испытания образцов из партии в аккредитованной лаборатории"
          ],
          "validity": "на партию"
        },
        {
          "id": "6д",
          "name": "Схема 6д",
          "applicableTo": "Серийное производство с сертифицированной СМК",
          "requirements": [
            "Испытания в аккредитованной лаборатории",
            "Сертификат СМК"
          ],
          "validity": "до 5 лет"
        }
      ]
    }
  },

  "riskClasses": {
    "class1": {
      "name": "СИЗ 1 класса (сертификация)",
      "description": "СИЗ сложной конструкции, защищающие от смертельных рисков и рисков причинения непоправимого вреда здоровью",
      "examples": [
        "СИЗОД фильтрующие и изолирующие",
        "СИЗ от падения с высоты",
        "СИЗ от поражения электрическим током",
        "СИЗ от химических факторов",
        "СИЗ от ионизирующих излучений",
        "СИЗ от высоких/низких температур с экстремальными показателями",
        "Каски защитные"
      ]
    },
    "class2": {
      "name": "СИЗ 2 класса (декларирование)",
      "description": "СИЗ простой конструкции, защищающие от минимальных рисков",
      "examples": [
        "СИЗ органа слуха",
        "СИЗ от общих производственных загрязнений",
        "СИЗ от механических воздействий (незначительных)",
        "Сигнальная одежда",
        "Дерматологические СИЗ"
      ]
    }
  },

  "safetyRequirements": {
    "generalRequirements": [
      "Эргономичность - удобство использования",
      "Минимальный вес при сохранении защитных свойств",
      "Безопасность материалов для пользователя",
      "Устойчивость к воздействию факторов внешней среды",
      "Сохранение защитных свойств в течение срока службы"
    ],
    "specificRequirements": {
      "sizeMarking": "Обязательная маркировка размера",
      "protectionLevel": "Указание уровня защиты",
      "limitations": "Указание ограничений по применению",
      "serviceLife": "Указание срока службы"
    }
  },

  "labeling": {
    "required": true,
    "elements": [
      "Наименование СИЗ",
      "Наименование изготовителя/импортера",
      "Защитные свойства и класс защиты",
      "Размер",
      "Дата изготовления/срок службы",
      "Обозначение стандарта или ТУ",
      "Знак соответствия ЕАС"
    ],
    "documentation": [
      "Инструкция по применению на русском языке",
      "Условия хранения",
      "Правила ухода и обслуживания",
      "Ограничения по применению"
    ]
  },

  "pricing": {
    "certificate": {
      "priceRange": "от 25 000 до 90 000 руб",
      "note": "Для СИЗ 1 класса риска"
    },
    "declaration": {
      "priceRange": "от 12 000 до 35 000 руб",
      "note": "Для СИЗ 2 класса риска"
    }
  },

  "timing": {
    "certificate": "от 20 до 45 рабочих дней",
    "declaration": "от 7 до 20 рабочих дней"
  },

  "importantNotes": [
    "Класс риска определяется по Приложению 4 к ТР ТС 019/2011",
    "СИЗ 1 класса требуют ТОЛЬКО сертификации",
    "СИЗ 2 класса допускают декларирование",
    "Бывшие в употреблении СИЗ НЕ подпадают под регламент",
    "Специализированные СИЗ (пожарные, медицинские, военные) регулируются отдельно",
    "Инструкция по применению обязательна на русском языке"
  ],

  "relatedRegulations": [
    {"id": "TR_TS_017_2011", "name": "О безопасности продукции лёгкой промышленности", "relation": "Для текстильных компонентов СИЗ"},
    {"id": "TR_TS_007_2011", "name": "О безопасности продукции для детей", "relation": "Не применяется к СИЗ для детей"},
    {"id": "TR_CU_031_2012", "name": "О безопасности сельскохозяйственных тракторов", "relation": "СИЗ для операторов"}
  ],

  "meta": {
    "createdAt": "2025-12-18",
    "createdBy": "GSG Parser",
    "version": "1.0",
    "sourceFile": "tr_ts_878.txt (N 878)",
    "productGroupsCount": 9
  }
}
